AUTHORS
CHANGES.rst
LICENSE
MANIFEST.in
README.rst
runshell.py
runtests.py
setup.cfg
setup.py
django_filters/__init__.py
django_filters/development.py
django_filters/production.py
django_filters/settings.py
django_filters/urls.py
docs/Makefile
docs/advanced_search.it.txt
docs/advanced_search.txt
docs/conf.py
docs/in
docs/index.txt
docs/install.txt
docs/make.bat
docs/readme.txt
docs/readme.txt~
docs/tests.txt
docs/usage.txt
docs/_build/doctrees/advanced_search.doctree
docs/_build/doctrees/advanced_search.it.doctree
docs/_build/doctrees/environment.pickle
docs/_build/doctrees/index.doctree
docs/_build/doctrees/install.doctree
docs/_build/doctrees/readme.doctree
docs/_build/doctrees/tests.doctree
docs/_build/doctrees/usage.doctree
docs/_build/doctrees/ref/filters.doctree
docs/_build/doctrees/ref/widgets.doctree
docs/_build/html/.buildinfo
docs/_build/html/advanced_search.html
docs/_build/html/advanced_search.it.html
docs/_build/html/genindex.html
docs/_build/html/index.html
docs/_build/html/install.html
docs/_build/html/objects.inv
docs/_build/html/readme.html
docs/_build/html/search.html
docs/_build/html/searchindex.js
docs/_build/html/tests.html
docs/_build/html/usage.html
docs/_build/html/_sources/advanced_search.it.txt
docs/_build/html/_sources/advanced_search.txt
docs/_build/html/_sources/index.txt
docs/_build/html/_sources/install.txt
docs/_build/html/_sources/readme.txt
docs/_build/html/_sources/tests.txt
docs/_build/html/_sources/usage.txt
docs/_build/html/_sources/ref/filters.txt
docs/_build/html/_sources/ref/widgets.txt
docs/_build/html/_static/ajax-loader.gif
docs/_build/html/_static/basic.css
docs/_build/html/_static/bootstrap.css
docs/_build/html/_static/bootstrap.js
docs/_build/html/_static/cloud.css
docs/_build/html/_static/cloud.js
docs/_build/html/_static/comment-bright.png
docs/_build/html/_static/comment-close.png
docs/_build/html/_static/comment.png
docs/_build/html/_static/doctools.js
docs/_build/html/_static/down-pressed.png
jmb.filters.egg-info/PKG-INFO
jmb.filters.egg-info/SOURCES.txt
jmb.filters.egg-info/dependency_links.txt
jmb.filters.egg-info/namespace_packages.txt
jmb.filters.egg-info/not-zip-safe
jmb.filters.egg-info/top_level.txt
