Metadata-Version: 1.1
Name: jmb.filters
Version: 0.1.7
Summary: jmb.filters is a reusable Django application for allowing users to filter querysets dynamically.
Home-page: http://docs.thux.it/jmb.filters
Author: Alex Gaynor, Alessandro Dentella
Author-email: sandro@e-den.it
License: BSD
Download-URL: https://bitbucket.org/jumboteam/jmb.filters
Platform: UNKNOWN
Classifier: Development Status :: 5 - Production/Stable
Classifier: Environment :: Web Environment
Classifier: Intended Audience :: Developers
Classifier: License :: OSI Approved :: BSD License
Classifier: Operating System :: OS Independent
Classifier: Programming Language :: Python
Classifier: Framework :: Django
